Classfile /C:/Users/tijerija/source/repos/GVM/GVM/sdk/Test.class
  Last modified Oct 10, 2019; size 432 bytes
  MD5 checksum fce621b8d69a8c1b853f6404e30b98cb
  Compiled from "Test.java"
class Test
  minor version: 0
  major version: 56
  flags: (0x0020) ACC_SUPER
  this_class: #4                          // Test
  super_class: #6                         // java/lang/Object
  interfaces: 0, fields: 0, methods: 4, attributes: 1
Constant pool:
   #1 = Methodref          #6.#19         // java/lang/Object."<init>":()V
   #2 = Methodref          #4.#20         // Test.call:()V
   #3 = Methodref          #4.#21         // Test.Print:(I)V
   #4 = Class              #22            // Test
   #5 = Methodref          #4.#19         // Test."<init>":()V
   #6 = Class              #23            // java/lang/Object
   #7 = Utf8               <init>
   #8 = Utf8               ()V
   #9 = Utf8               Code
  #10 = Utf8               LineNumberTable
  #11 = Utf8               call
  #12 = Utf8               StackMapTable
  #13 = Utf8               Print
  #14 = Utf8               (I)V
  #15 = Utf8               main
  #16 = Utf8               ([Ljava/lang/String;)V
  #17 = Utf8               SourceFile
  #18 = Utf8               Test.java
  #19 = NameAndType        #7:#8          // "<init>":()V
  #20 = NameAndType        #11:#8         // call:()V
  #21 = NameAndType        #13:#14        // Print:(I)V
  #22 = Utf8               Test
  #23 = Utf8               java/lang/Object
{
  public Test();
    descriptor: ()V
    flags: (0x0001) ACC_PUBLIC
    Code:
      stack=1, locals=1, args_size=1
         0: aload_0
         1: invokespecial #1                  // Method java/lang/Object."<init>":()V
         4: aload_0
         5: invokevirtual #2                  // Method call:()V
         8: return
      LineNumberTable:
        line 3: 0
        line 4: 4
        line 5: 8

  public void call();
    descriptor: ()V
    flags: (0x0001) ACC_PUBLIC
    Code:
      stack=2, locals=2, args_size=1
         0: iconst_0
         1: istore_1
         2: iload_1
         3: bipush        10
         5: if_icmpge     18
         8: iload_1
         9: invokestatic  #3                  // Method Print:(I)V
        12: iinc          1, 1
        15: goto          2
        18: return
      LineNumberTable:
        line 8: 0
        line 9: 8
        line 8: 12
        line 11: 18
      StackMapTable: number_of_entries = 2
        frame_type = 252 /* append */
          offset_delta = 2
          locals = [ int ]
        frame_type = 250 /* chop */
          offset_delta = 15

  public static native void Print(int);
    descriptor: (I)V
    flags: (0x0109) ACC_PUBLIC, ACC_STATIC, ACC_NATIVE

  public static void main(java.lang.String[]);
    descriptor: ([Ljava/lang/String;)V
    flags: (0x0009) ACC_PUBLIC, ACC_STATIC
    Code:
      stack=2, locals=2, args_size=1
         0: new           #4                  // class Test
         3: dup
         4: invokespecial #5                  // Method "<init>":()V
         7: astore_1
         8: return
      LineNumberTable:
        line 16: 0
        line 20: 8
}
SourceFile: "Test.java"
